github_action_utils.py
github_action_utils-1.1.0.dist-info/LICENSE
github_action_utils-1.1.0.dist-info/METADATA
github_action_utils-1.1.0.dist-info/WHEEL
github_action_utils-1.1.0.dist-info/top_level.txt
github_action_utils-1.1.0.dist-info/RECORD
