Metadata-Version: 2.1
Name: github-action-utils
Version: 1.1.0
Summary: Collection of python functions that can be used to run GitHub Action Workflow Commands
Home-page: https://github.com/saadmk11/github-action-utils
Author: Maksudul Haque
Author-email: saad.mk112@gmail.com
License: MIT
Classifier: License :: OSI Approved :: MIT License
Classifier: Programming Language :: Python :: 3
Classifier: Programming Language :: Python :: 3 :: Only
Classifier: Programming Language :: Python :: 3.6
Classifier: Programming Language :: Python :: 3.7
Classifier: Programming Language :: Python :: 3.8
Classifier: Programming Language :: Python :: 3.9
Classifier: Programming Language :: Python :: 3.10
Classifier: Programming Language :: Python :: 3.11
Classifier: Programming Language :: Python :: Implementation :: CPython
Requires-Python: >=3.6.0
License-File: LICENSE
